<?xml version="1.0" encoding="utf-8" ?>
<dwsync>
<file name="33ddd22e4b_qr.png" server="45.132.243.64/domains/innovet.com.mx/innovet/public/ceers/" local="133676102800658203" remote="133571721600000000" Dst="0" />
<file name="Certificado de Verificación.pdf" server="45.132.243.64/domains/innovet.com.mx/innovet/public/ceers/" local="133676102806245977" remote="133590021000000000" Dst="0" />
<file name="FACTURA TOYOTA HILUX 2023.pdf" server="45.132.243.64/domains/innovet.com.mx/innovet/public/ceers/" local="133676102806720784" remote="133590021000000000" Dst="0" />
<file name="INES BE EXEN.pdf" server="45.132.243.64/domains/innovet.com.mx/innovet/public/ceers/" local="133676102810398502" remote="133590021000000000" Dst="0" />
<file name="LICENCIAS DE CONDUCIR BE EXEN.pdf" server="45.132.243.64/domains/innovet.com.mx/innovet/public/ceers/" local="133676102812195112" remote="133590021000000000" Dst="0" />
<file name="POLÍTICAS ARRENDAMIENTO HILUX BE EXEN.pdf" server="45.132.243.64/domains/innovet.com.mx/innovet/public/ceers/" local="133676102816428930" remote="133590021000000000" Dst="0" />
<file name="SOL090407QG0FQRO0000000391.pdf" server="45.132.243.64/domains/innovet.com.mx/innovet/public/ceers/" local="133676102816937015" remote="133604587200000000" Dst="0" />
<file name="RESPONSIVAS HILUX BE EXEN.pdf" server="45.132.243.64/domains/innovet.com.mx/innovet/public/ceers/" local="133676102821197686" remote="133590021000000000" Dst="0" />
<file name="TENENCIA TOYOTA HILUZ_PODER EJECUTIVO DE QUERETARO_ R4 14349077.pdf" server="45.132.243.64/domains/innovet.com.mx/innovet/public/ceers/" local="133676102821738602" remote="133590021000000000" Dst="0" />
<file name="TAREJTA DE CIRCULACION TOYOTA.jpeg.jpeg" server="45.132.243.64/domains/innovet.com.mx/innovet/public/ceers/" local="133676102822238905" remote="133590021000000000" Dst="0" />
<file name="TOYOTA HILUX 2023.jpeg" server="45.132.243.64/domains/innovet.com.mx/innovet/public/ceers/" local="133676102826288774" remote="133590021000000000" Dst="0" />
<file name="Verificacion Hilux.pdf" server="45.132.243.64/domains/innovet.com.mx/innovet/public/ceers/" local="133676102829782131" remote="133590021000000000" Dst="0" />
<file name="Verificación Hilux ENE-JUL 2024.pdf" server="45.132.243.64/domains/innovet.com.mx/innovet/public/ceers/" local="133676102830324199" remote="133590021000000000" Dst="0" />
</dwsync>